{"name":"Bogomap.GitHub.io","tagline":"Página principal de BogoMap","body":"#BogoMap\r\n\r\n**Bienvenido al Mapa gratuito del Sistema de Transporte de Bogotá**\r\n\r\nEsta es una iniciativa privada e independiente que busca ofrecer un mapa gratuitamente a los pasajeros que se desplazan es los nuevos sistemas de transporte de Bogotá (el sistema [BRT](https://es.wikipedia.org/wiki/Autob%C3%BAs_de_tr%C3%A1nsito_r%C3%A1pido) y el sistema de transporte).\r\n\r\nEsta iniciativa busca ofrecer a los ciudadanos toda la información en un solo lugar, necesaria para poder desplazarse, ya que actualmente no está disponible en medios impresos. La única información que se consigue es digital, por medio de Internet, la cual no es práctica cuando se está en la calle, además que no todos los ciudadanos tienen acceso a Internet de manera permanente y aún menos en dispositivos móviles.\r\n\r\nLa iniciativa busca crear una comunidad de interesados en el mapa, de manera que la comunidad misma retroalimente el mapa enviando sus correcciones o novedades, y a cambio ellos reciban una gratificación, al mismo tiempo que se va construyendo un mejor mapa.\r\n\r\nSi quieres colaborar, puedes ir a la sección [cómo colaborar](Cómo-colaborar).\r\n\r\nSíguenos en las redes sociales:\r\n\r\n* [Twitter](https://twitter.com/bogomap)\r\n* [Facebook](https://www.facebook.com/BogoMap)\r\n* [Google Plus](https://google.com/+Bogomap-gratis)\r\n","google":"","note":"Don't delete this file! It's used internally to help with page regeneration."}